impulse/__init__.py
impulse/base.py
impulse/mhsampler.py
impulse/online_updates.py
impulse/product_space.py
impulse/proposals.py
impulse/ptsampler.py
impulse_mcmc-1.0.0.dist-info/LICENSE
impulse_mcmc-1.0.0.dist-info/METADATA
impulse_mcmc-1.0.0.dist-info/WHEEL
impulse_mcmc-1.0.0.dist-info/top_level.txt
impulse_mcmc-1.0.0.dist-info/RECORD
