Metadata-Version: 2.2
Name: impulse-mcmc
Version: 1.0.0
Summary: A rewrite of PTMCMCSampler focusing on modularity
Home-page: https://github.com/AaronDJohnson/impulse
Author: Aaron D. Johnson
Author-email: "Aaron D. Johnson" <aaron9035@gmail.com>
Project-URL: Homepage, https://github.com/AaronDJohnson/impulse_mcmc
Project-URL: Issues, https://github.com/AaronDJohnson/impulse_mcmc/issues
Classifier: Programming Language :: Python :: 3
Classifier: Operating System :: OS Independent
Requires-Python: >=3.10
License-File: LICENSE
Requires-Dist: numpy>=2.2.2
Requires-Dist: scipy>=1.15.1
Requires-Dist: tqdm>=4.67.1
